{
    "blue_candidates": [
        {"name": "Ryze", "confidence": 10},
        {"name": "Xin Zhao", "confidence": 9},
        {"name": "Aurora", "confidence": 9},
        {"name": "Ambessa", "confidence": 8},
        {"name": "Annie", "confidence": 8},
        {"name": "Sivir", "confidence": 7},
        {"name": "Lucian", "confidence": 7},
        {"name": "Gwen", "confidence": 7},
        {"name": "Alistar", "confidence": 7},
        {"name": "Nautilus", "confidence": 6},
        {"name": "Jarvan IV", "confidence": 6},
        {"name": "Rakan", "confidence": 6},
        {"name": "Miss Fortune", "confidence": 6},
        {"name": "K'Sante", "confidence": 5},
        {"name": "Rumble", "confidence": 5},
        {"name": "Kai'Sa", "confidence": 5},
        {"name": "Leona", "confidence": 5},
        {"name": "Jhin", "confidence": 4},
        {"name": "Renekton", "confidence": 4},
        {"name": "Trundle", "confidence": 4},
        {"name": "Lee Sin", "confidence": 4},
        {"name": "Aphelios", "confidence": 3},
        {"name": "Neeko", "confidence": 3},
        {"name": "Vi", "confidence": 3},
        {"name": "Nocturne", "confidence": 3},
        {"name": "Yone", "confidence": 2},
        {"name": "Thresh", "confidence": 2},
        {"name": "Poppy", "confidence": 2},
        {"name": "Maokai", "confidence": 2},
        {"name": "Sejuani", "confidence": 2}
    ],
    "red_candidates": [
        {"name": "Annie", "confidence": 10},
        {"name": "Xin Zhao", "confidence": 9},
        {"name": "Ryze", "confidence": 9},
        {"name": "Rumble", "confidence": 8},
        {"name": "Trundle", "confidence": 8},
        {"name": "Ezreal", "confidence": 8},
        {"name": "Nautilus", "confidence": 7},
        {"name": "Ziggs", "confidence": 7},
        {"name": "Jarvan IV", "confidence": 7},
        {"name": "Alistar", "confidence": 6},
        {"name": "Rakan", "confidence": 6},
        {"name": "Aurora", "confidence": 6},
        {"name": "Ambessa", "confidence": 5},
        {"name": "Sion", "confidence": 5},
        {"name": "Renekton", "confidence": 5},
        {"name": "Corki", "confidence": 5},
        {"name": "Jhin", "confidence": 4},
        {"name": "Gwen", "confidence": 4},
        {"name": "Leona", "confidence": 4},
        {"name": "Sivir", "confidence": 4},
        {"name": "Lee Sin", "confidence": 4},
        {"name": "Aphelios", "confidence": 3},
        {"name": "Neeko", "confidence": 3},
        {"name": "Skarner", "confidence": 3},
        {"name": "Rell", "confidence": 3},
        {"name": "Karma", "confidence": 3},
        {"name": "Ahri", "confidence": 2},
        {"name": "Vi", "confidence": 2},
        {"name": "Bard", "confidence": 2},
        {"name": "Elise", "confidence": 2}
    ]
}